README.md
setup.cfg
setup.py
mbq/__init__.py
mbq.pubsub.egg-info/PKG-INFO
mbq.pubsub.egg-info/SOURCES.txt
mbq.pubsub.egg-info/dependency_links.txt
mbq.pubsub.egg-info/not-zip-safe
mbq.pubsub.egg-info/requires.txt
mbq.pubsub.egg-info/top_level.txt
mbq/pubsub/__init__.py
mbq/pubsub/__init__.pyi
mbq/pubsub/__version__.py
mbq/pubsub/admin.py
mbq/pubsub/apps.py
mbq/pubsub/constants.py
mbq/pubsub/consumer.py
mbq/pubsub/decorators.py
mbq/pubsub/exceptions.py
mbq/pubsub/models.py
mbq/pubsub/publishers.py
mbq/pubsub/py.typed
mbq/pubsub/settings.py
mbq/pubsub/utils.py
mbq/pubsub/management/__init__.py
mbq/pubsub/management/commands/__init__.py
mbq/pubsub/management/commands/pubsub.py
mbq/pubsub/migrations/0001_initial.py
mbq/pubsub/migrations/0002_auto_20190405_1418.py
mbq/pubsub/migrations/__init__.py
protos/__init__.py
protos/test_pb2.py
tests/__init__.py
tests/message_handlers.py
tests/settings.py
tests/urls.py
tests/wsgi.py
tests/management/__init__.py
tests/management/commands/__init__.py
tests/management/commands/publish_exception.py
tests/management/commands/publish_json.py
tests/management/commands/publish_proto.py
tests/management/commands/publish_proto_exception.py
tests/management/commands/publish_with_envelope.py